justbases/__init__.py
justbases/_config.py
justbases/_constants.py
justbases/_display.py
justbases/_division.py
justbases/_errors.py
justbases/_nats.py
justbases/_rationals.py
justbases/version.py
justbases-0.15.2.dist-info/LICENSE
justbases-0.15.2.dist-info/METADATA
justbases-0.15.2.dist-info/WHEEL
justbases-0.15.2.dist-info/top_level.txt
justbases-0.15.2.dist-info/RECORD
