Metadata-Version: 2.1
Name: justbases
Version: 0.15.2
Summary: "conversion of ints and rationals to any base"
Home-page: https://github.com/mulkieran/justbases
Author: Anne Mulhern
Author-email: amulhern@redhat.com
License: LGPL-2.1-or-later
Platform: Linux
Classifier: Development Status :: 4 - Beta
Classifier: Intended Audience :: Developers
Classifier: License :: OSI Approved :: GNU Lesser General Public License v2 or later (LGPLv2+)
Classifier: Operating System :: POSIX :: Linux
Classifier: Programming Language :: Python
Classifier: Programming Language :: Python :: 3
Classifier: Programming Language :: Python :: Implementation :: CPython
Classifier: Programming Language :: Python :: Implementation :: PyPy
Classifier: Topic :: Software Development :: Libraries
Classifier: Topic :: Scientific/Engineering :: Mathematics
License-File: LICENSE
